wikimapia_api
